README.md
setup.py
mmax2conll/__init__.py
mmax2conll/__main__.py
mmax2conll/conll_converters.py
mmax2conll/conll_writers.py
mmax2conll/constants.py
mmax2conll/main.py
mmax2conll/mmax_document_readers.py
mmax2conll/mmax_item_readers.py
mmax2conll/util.py
mmax2conll.egg-info/PKG-INFO
mmax2conll.egg-info/SOURCES.txt
mmax2conll.egg-info/dependency_links.txt
mmax2conll.egg-info/requires.txt
mmax2conll.egg-info/top_level.txt